ezeeresult/__init__.py
ezeeresult/exportdata.py
ezeeresult/ezeeresult.py
ezeeresult/helpers.py
ezeeresult/parsehtml.py
ezeeresult/parsepdf.py
ezeeresult/savefile.py
ezeeresult/skeleton.py
ezeeresult-0.1.3.dist-info/LICENSE.txt
ezeeresult-0.1.3.dist-info/METADATA
ezeeresult-0.1.3.dist-info/WHEEL
ezeeresult-0.1.3.dist-info/entry_points.txt
ezeeresult-0.1.3.dist-info/top_level.txt
ezeeresult-0.1.3.dist-info/RECORD
