Metadata-Version: 2.1
Name: ezeeresult
Version: 0.1.3
Summary: Marks scraper for MCA (REVISED 2020) latest semester.
Home-page: https://github.com/be-krishna/ezeeresult
Author: be-krishna
Author-email: bkshgnj@gmail.com
License: MIT
Platform: any
Classifier: Development Status :: 4 - Beta
Classifier: Programming Language :: Python
License-File: LICENSE.txt
Requires-Dist: requests
Requires-Dist: numpy
Requires-Dist: pandas
Requires-Dist: playwright
Requires-Dist: tabula-py
Requires-Dist: beautifulsoup4
Requires-Dist: openpyxl
Requires-Dist: rich
Requires-Dist: click
Requires-Dist: importlib-metadata ; python_version < "3.8"
Provides-Extra: testing
Requires-Dist: setuptools ; extra == 'testing'
Requires-Dist: pytest ; extra == 'testing'
Requires-Dist: pytest-cov ; extra == 'testing'
